pd3/__init__.py
pd3-0.0.1.dist-info/LICENSE
pd3-0.0.1.dist-info/METADATA
pd3-0.0.1.dist-info/WHEEL
pd3-0.0.1.dist-info/top_level.txt
pd3-0.0.1.dist-info/RECORD
