Metadata-Version: 2.1
Name: pd3
Version: 0.0.1
Summary: PD3 is a modern, accelerated library for discrete dislocation dynamics.
Home-page: https://github.com/dmadisetti/pd3/
Author: Dylan Madisetti
Author-email: madisetti@jhu.edu
License: MIT
Download-URL: https://github.com/dmadisetti/pd3/tags
Keywords: pd3 discrete dislocation dynamics ddd
Platform: UNKNOWN
Classifier: Development Status :: 1 - Planning
Classifier: Topic :: Scientific/Engineering
Classifier: Topic :: Scientific/Engineering :: Physics
Classifier: Topic :: Scientific/Engineering :: Mathematics
Classifier: Topic :: Scientific/Engineering :: Artificial Intelligence
Classifier: Intended Audience :: Science/Research
Requires-Dist: absl-py (>=0.7.0)
Requires-Dist: numpy (<2.0,>=1.16.0)
Requires-Dist: protobuf (>=3.9.2)
Requires-Dist: wheel (>=0.26)
Requires-Dist: six (>=1.12.0)
Requires-Dist: typing-extensions (>=3.7.4)
Requires-Dist: scipy (==1.4.1)
